python_funtranslation/__init__.py
python_funtranslation/python_funtranslation.py
python_funtranslation-0.1.0.dist-info/LICENSE
python_funtranslation-0.1.0.dist-info/METADATA
python_funtranslation-0.1.0.dist-info/WHEEL
python_funtranslation-0.1.0.dist-info/RECORD
